sktaip_cli/__init__.py
sktaip_cli/cli.py
sktaip_cli/docker.py
sktaip_cli/exec.py
sktaip_cli/port.py
sktaip_cli/progress.py
sktaip_cli/subapp_cli.py
sktaip_cli/utils.py
sktaip_cli-0.1.10.dist-info/METADATA
sktaip_cli-0.1.10.dist-info/WHEEL
sktaip_cli-0.1.10.dist-info/entry_points.txt
sktaip_cli-0.1.10.dist-info/RECORD
