Metadata-Version: 2.3
Name: sktaip-cli
Version: 0.1.10
Summary: AIX Platform CLI
License: Proprietary
Author: AIX Enterprise
Requires-Python: >=3.10,<4.0
Classifier: License :: Other/Proprietary License
Classifier: Programming Language :: Python :: 3
Classifier: Programming Language :: Python :: 3.10
Classifier: Programming Language :: Python :: 3.11
Classifier: Programming Language :: Python :: 3.12
Classifier: Programming Language :: Python :: 3.13
Requires-Dist: pydantic[email] (>=2.10.0,<2.11.0)
Requires-Dist: sktaip_api (==0.1.9)
